README.md
setup.py
lloyd/__init__.py
lloyd/lloyd.py
lloyd.egg-info/PKG-INFO
lloyd.egg-info/SOURCES.txt
lloyd.egg-info/dependency_links.txt
lloyd.egg-info/requires.txt
lloyd.egg-info/top_level.txt